LICENSE.md
MANIFEST.in
README.md
__init__.py
climate.py
constants.py
inout.py
readme_pypi
setup.py
aostools.egg-info/PKG-INFO
aostools.egg-info/SOURCES.txt
aostools.egg-info/dependency_links.txt
aostools.egg-info/not-zip-safe
aostools.egg-info/requires.txt
aostools.egg-info/top_level.txt