Metadata-Version: 1.0
Name: aostools
Version: 2.3.2
Summary: Helper functions for scientific postprocessing and analysis of netCDF data
Home-page: https://github.com/mjucker/aostools
Author: Martin Jucker
Author-email: coding@martinjucker.com
License: GPLv3
Keywords: atmospheric oceanic science netcdf analysis tools
Platform: UNKNOWN
